Lab5/group03_lab5_part1.v
//ignore the test bench
// used as the test bench 
module testbench;

 reg [7:0] OPERAND1,OPERAND2;
 reg [3:0] ALUOP;
 wire [7:0] ALURESULT;


 alu model1(OPERAND1,OPERAND2, ALURESULT, ALUOP); 

 initial
 begin
 //$monitor($time,"OPERAND1:%b, OPERAND2:%b, ALUOP:%b ALURESULT:%b",OPERAND1,OPERAND2,ALUOP,ALURESULT);
 $dumpfile("wavedata.vcd");
 $dumpvars(0,model1);
 #100 $finish;
 end

 initial
 begin
 OPERAND1=8'd5;
 OPERAND2=8'd1;
 ALUOP=3'b000;


 #10
 OPERAND1=8'd54;
 ALUOP=3'b001;
 #1
 OPERAND2=8'd45;
 ALUOP=3'b001;
 #10ALUOP=3'b010; 
 #10ALUOP=3'b011;
 
 end
endmodule








module alu(DATA1, DATA2, RESULT, SELECT);
 input [7:0] DATA1,DATA2; // INPUT DATA TO THE ALU
 input [3:0] SELECT;       // THIS WILL DECIDE THE CORRESPONDING OUTPUT RESULT FROM THE OUTPUTS OF FUNCTIONAL UNITS
 output [7:0] RESULT;
 wire [7:0] FORWARD_OUT, ADD_OUT, AND_OUT, OR_OUT; // these will be the outputs of the functional units

 FORWARD forward_result(DATA2, FORWARD_OUT); //FORWARD FUNCTION  
 ADD add_result(DATA1,DATA2, ADD_OUT);      //ADD FUNCTION
 AND and_result(DATA1, DATA2, AND_OUT);     //AND  FUNCTION
 OR or_result(DATA1, DATA2, OR_OUT);        //OR FUNCTION
 MUX mux_result(SELECT,FORWARD_OUT, ADD_OUT, AND_OUT, OR_OUT,RESULT);  // RESULT OUTPUT WILL BE DECIDED FROM THE OUTPUTS OF THE FUNCTIONAL UNITS
 
endmodule





module FORWARD(DATA2, FORWARD_OUT);   //JUST FORWARD THE OUTPUT (loadi,mov)
 input [7:0] DATA2;
 output [7:0] FORWARD_OUT;

 assign  #1FORWARD_OUT=DATA2;  //DELAY 1 UNIT

endmodule


module ADD(DATA1,DATA2, ADD_OUT); //Addition and substraction operations
input [7:0] DATA1,DATA2;
output [7:0]ADD_OUT;

assign  #2ADD_OUT=DATA1+DATA2;  //DELAY 2 UNITS

endmodule

module AND(DATA1, DATA2, AND_OUT); //AND OPERATION
 input [7:0] DATA1,DATA2;
 output [7:0] AND_OUT;

 assign  #1AND_OUT=DATA1&DATA2;  //DELAY 1 UNIT

endmodule

module OR(DATA1, DATA2, OR_OUT); //OR OPERATION
 input [7:0] DATA1,DATA2;
 output [7:0] OR_OUT;

 assign  #1OR_OUT=DATA1|DATA2;  //DELAY 1 UNIT

endmodule


module MUX(SELECT,FORWARD_OUT, ADD_OUT, AND_OUT, OR_OUT,RESULT); //THE MUX IS USED TO GET THE RESULT OF THE DESIRED FUNCTION

input [7:0] FORWARD_OUT, ADD_OUT, AND_OUT, OR_OUT;
input [3:0] SELECT;
output reg [7:0] RESULT;



always @ (SELECT,FORWARD_OUT, ADD_OUT, AND_OUT, OR_OUT)
begin
  if(SELECT == 3'b000)
  begin
    RESULT = FORWARD_OUT;
  end

  else if(SELECT == 3'b001)
  begin
    RESULT = ADD_OUT;
  end  

  else if(SELECT == 3'b010)
  begin
    RESULT = AND_OUT;
  end

  else if(SELECT == 3'b011)
  begin
    RESULT = OR_OUT;
  end  

  else
  begin
    RESULT = OR_OUT;
  end  
end
endmodule

Lab5/wavedata.vcd
$date
	Tue Jan 11 22:41:29 2022
$end
$version
	Icarus Verilog
$end
$timescale
	1s
$end
$scope module testbench $end
$scope module model1 $end
$var wire 8 ! DATA1 [7:0] $end
$var wire 8 " DATA2 [7:0] $end
$var wire 4 # SELECT [3:0] $end
$var wire 8 $ RESULT [7:0] $end
$var wire 8 % OR_OUT [7:0] $end
$var wire 8 & FORWARD_OUT [7:0] $end
$var wire 8 ' AND_OUT [7:0] $end
$var wire 8 ( ADD_OUT [7:0] $end
$scope module add_result $end
$var wire 8 ) DATA1 [7:0] $end
$var wire 8 * DATA2 [7:0] $end
$var wire 8 + ADD_OUT [7:0] $end
$upscope $end
$scope module and_result $end
$var wire 8 , AND_OUT [7:0] $end
$var wire 8 - DATA1 [7:0] $end
$var wire 8 . DATA2 [7:0] $end
$upscope $end
$scope module forward_result $end
$var wire 8 / DATA2 [7:0] $end
$var wire 8 0 FORWARD_OUT [7:0] $end
$upscope $end
$scope module mux_result $end
$var wire 8 1 ADD_OUT [7:0] $end
$var wire 8 2 AND_OUT [7:0] $end
$var wire 8 3 FORWARD_OUT [7:0] $end
$var wire 4 4 SELECT [3:0] $end
$var wire 8 5 OR_OUT [7:0] $end
$var reg 8 6 RESULT [7:0] $end
$upscope $end
$scope module or_result $end
$var wire 8 7 DATA1 [7:0] $end
$var wire 8 8 DATA2 [7:0] $end
$var wire 8 9 OR_OUT [7:0] $end
$upscope $end
$upscope $end
$upscope $end
$enddefinitions $end
#0
$dumpvars
bx 9
b1 8
b101 7
bx 6
bx 5
b0 4
bx 3
bx 2
bx 1
bx 0
b1 /
b1 .
b101 -
bx ,
bx +
b1 *
b101 )
bx (
bx '
bx &
bx %
bx $
b0 #
b1 "
b101 !
$end
#1
b1 $
b1 6
b101 %
b101 5
b101 9
b1 '
b1 ,
b1 2
b1 &
b1 0
b1 3
#2
b110 (
b110 +
b110 1
#10
b110 $
b110 6
b1 #
b1 4
b110110 !
b110110 )
b110110 -
b110110 7
#11
b0 '
b0 ,
b0 2
b110111 %
b110111 5
b110111 9
b101101 "
b101101 *
b101101 .
b101101 /
b101101 8
#12
b100100 '
b100100 ,
b100100 2
b111111 %
b111111 5
b111111 9
b101101 &
b101101 0
b101101 3
#13
b1100011 $
b1100011 6
b1100011 (
b1100011 +
b1100011 1
#21
b100100 $
b100100 6
b10 #
b10 4
#31
b111111 $
b111111 6
b11 #
b11 4
