lab5part3/submission/cpu(group03_part3).v
//cpu for lab 5 part 3
//GROUP 3
//CO224
`include "group03_lab5_part1(alu).v"
`include "group03_lab5_part2(reg_file).v"

module cpu(PC,INSTRUCTION,CLK,RESET);

 input [31:0] INSTRUCTION;   //Current instruction to be executed-32 bits long
 input CLK,RESET;            //clock and reset signals
 output reg [31:0] PC=-32'd4;       //PC contains the address of the intruction to be read
 
 wire [31:0] PCOUT;
 wire [7:0] OPCODE,IMMEDIATE,REGOUT1,REGOUT2,OPERAND2,REGOUT2COMPLIMENT,VALUE2,ALURESULT;
 wire [2:0] READREG1,READREG2,WRITEREG,ALUOP;
 wire MUXREGOUT2,MUXIMMEDIATE,WRITEENABLE;

 assign OPCODE=INSTRUCTION[31:24];
 assign READREG1=INSTRUCTION[10:8];  //INSTRUCTION[15:8] PROVIDES THE ADDRESS OF THE FIRST REGISTER.HOWEVER THE ADDRESS CAN BE INTERPRETED BY USING ONLY THE FIRST 3 BITS
 assign READREG2=INSTRUCTION[2:0];   //INSTRUCTION[7:0] PROVIDES THE ADDRESS OF THE SECOND REGISTER.HOWEVER THE ADDRESS CAN BE INTERPRETED BY USING ONLY THE FIRST 3 BITS
 assign IMMEDIATE=INSTRUCTION[7:0];   //THE IMMEDIATE VALUE OF loadi INSTRUCTION
 assign WRITEREG=INSTRUCTION[18:16]; //INSTRUCTION[23:16] PROVIDES THE ADDRESS OF THE WRITE REGISTER.HOWEVER THE ADDRESS CAN BE INTERPRETED BY USING ONLY THE FIRST 3 BITS
 

 control_unit control_signals(OPCODE,MUXREGOUT2,MUXIMMEDIATE,WRITEENABLE,ALUOP); //generate control unit signals
 reg_file register_operation(ALURESULT,REGOUT1,REGOUT2,WRITEREG,READREG1,READREG2,WRITEENABLE,CLK,RESET); //8*8 REGISTER OPERATIONS
 compliment compliment_operation(REGOUT2,REGOUT2COMPLIMENT); //compliement of the REGOUT2 value
 compliment_mux sub_or_not(VALUE2,REGOUT2,REGOUT2COMPLIMENT,MUXREGOUT2); //check whether it is an sub operation and get the appropriate result
 immediate_mux ValueOPERAND2(OPERAND2,VALUE2,IMMEDIATE,MUXIMMEDIATE); //check whether the value of operand2 is immediate or the register value and get the output
 alu alu_result(REGOUT1, OPERAND2, ALURESULT, ALUOP);  //ALU operation
 adder pc_adder(PC,PCOUT);// Increment the pc by 4



 //pc update operation

 always @(posedge CLK)
 begin
  if(RESET==1'b0) //if reset is not enabled next instruction
  begin
   #1 PC=PCOUT;
  end
  else
  begin
    #1 PC=32'd0; //if reset is enabled set PC to 0
  end
 end


endmodule


//control unit operations
module control_unit(OPCODE,MUXREGOUT2,MUXIMMEDIATE,WRITEENABLE,ALUOP);
 input [7:0] OPCODE;
 output reg MUXREGOUT2,MUXIMMEDIATE,WRITEENABLE;
 output reg [2:0] ALUOP;

 always @(OPCODE)
 begin

 #1 //one time unit delay for instruction decoding
 case(OPCODE)

  8'b00000000: //OPCODE FOR loadi instructions.carried out by FORWARD function in ALU.
  begin
    ALUOP=3'b000;
    MUXIMMEDIATE=1'b1;   //immediate value is taken in loadi instruction insted of the value in register2
    MUXREGOUT2=1'b1;    //2's comliment is not considered in loadi
    WRITEENABLE=1'b1;   //a value is written to a register 
  end

  8'b00000001: //OPCODE for mov instructions.both carried out by ADD function in ALU
  begin
    ALUOP=3'b000;
    MUXIMMEDIATE=1'b0;  //value in register2 is taken in mov
    MUXREGOUT2=1'b1;    //2's comliment is not considered in mov
    WRITEENABLE=1'b1;     //a value is written to a register  
  end

  8'b00000010: //OPCODE for add instructions.carried out by ADD function in ALU.
  begin
    ALUOP=3'b001;
    MUXIMMEDIATE=1'b0;  //value in register2 is taken in add
    MUXREGOUT2=1'b1;    //2's comliment is not considered in add
    WRITEENABLE=1'b1;     //a value is written to a register      
  end

  8'b00000011: //OPCODE for sub instructions.both carried out by ADD function in ALU.
  begin
    ALUOP=3'b001;
    MUXIMMEDIATE=1'b0;  //value in register2 is taken in sub
    MUXREGOUT2=1'b0;    //2's compliment is considered in sub
    WRITEENABLE=1'b1;     //a value is written to a register        
  end

  8'b00000100:             //OPCODE for and instructions.carried out by AND function in ALU
  begin
    ALUOP=3'b010;
    MUXIMMEDIATE=1'b0;  //value in register2 is taken in and
    MUXREGOUT2=1'b1;    //2's compliment is not considered in and
    WRITEENABLE=1'b1;     //a value is written to a register        
  end

  8'b00000101:           //OPCODE for or instructions.carried out by OR function in ALU
  begin
    ALUOP=3'b011;
    MUXIMMEDIATE=1'b0;  //value in register2 is taken in or
    MUXREGOUT2=1'b1;    //2's compliment is not considered in or
    WRITEENABLE=1'b1;     //a value is written to a register           
  end

  default: 
  begin
    ALUOP=3'b011;           //other instructions are not yet used.assigned to OR function.this doesn't mean anything.
    MUXIMMEDIATE=1'b0;  //doesn't matter either way.can be either 1 or 0
    MUXREGOUT2=1'b1;    //doesn't matter either way.can be either 1 or 0
    WRITEENABLE=1'b0;     //write is not enabled to make sure the values in registeres are not replaced by garbage values           
  end
 endcase

 

 end

endmodule

//this module will compute 2's compliment of a given value
module compliment(REGOUT2,REGOUT2COMPLIMENT);
 input [7:0] REGOUT2;
 output reg [7:0] REGOUT2COMPLIMENT;
  
  always @(REGOUT2)
  begin
  #1 REGOUT2COMPLIMENT= ~REGOUT2+1'b1; //taking 2's compliment with unit time delay
  end
endmodule


//this mux will choose between register2 value and it's 2's compliment based on control signal
module compliment_mux(VALUE2,REGOUT2,REGOUT2COMPLIMENT,MUXREGOUT2);
 input [7:0] REGOUT2,REGOUT2COMPLIMENT;
 input MUXREGOUT2;
 output reg [7:0] VALUE2;

 always @(REGOUT2,REGOUT2COMPLIMENT,MUXREGOUT2)
 begin

  if(MUXREGOUT2==1'b0) //2's compliment should be the output
  begin
   VALUE2=REGOUT2COMPLIMENT;
  end

  else        //REGOUT2 value should be the output
  begin
   VALUE2=REGOUT2;
  end


 end
endmodule



//this mux will choose between register value after compliment(VALUE2) and an immediate value based on control signal
module immediate_mux(OPERAND2,VALUE2,IMMEDIATE,MUXIMMEDIATE);
 input [7:0] VALUE2,IMMEDIATE;
 input MUXIMMEDIATE;
 output reg [7:0] OPERAND2;

 always @(VALUE2,IMMEDIATE,MUXIMMEDIATE)
 begin

  if(MUXIMMEDIATE==1'b0) //REGISTER VALUE IS CONSIDERED
  begin
   OPERAND2=VALUE2;
  end

  else        //IMMEDIATE VALUE IS CONSIDERED
  begin
   OPERAND2=IMMEDIATE;
  end


 end
endmodule



//get the pc value
module adder(PC,PCOUT);
 input [31:0] PC;
 output [31:0] PCOUT;

 assign #1 PCOUT=PC+4;    //increment PC by 4
endmodule

lab5part3/submission/group03_lab5_part1(alu).v

/* //used as the test bench.commented out 
module testbench;

 reg [7:0] OPERAND1,OPERAND2;
 reg [2:0] ALUOP;
 wire [7:0] ALURESULT;


 alu model1(OPERAND1,OPERAND2, ALURESULT, ALUOP); 

 initial
 begin
 //$monitor($time,"OPERAND1:%b, OPERAND2:%b, ALUOP:%b ALURESULT:%b",OPERAND1,OPERAND2,ALUOP,ALURESULT);
 $dumpfile("wavedata.vcd");
 $dumpvars(0,model1);
 #100 $finish;
 end

 initial
 begin
 OPERAND1=8'd5;
 OPERAND2=8'd1;
 ALUOP=3'b000;


 #10
 OPERAND1=8'd54;
 ALUOP=3'b001;
 #1
 OPERAND2=8'd45;
 ALUOP=3'b001;
 #10ALUOP=3'b010; 
 #10ALUOP=3'b011;
 
 end
endmodule

*/






module alu(DATA1, DATA2, RESULT, SELECT);
 input [7:0] DATA1,DATA2; // INPUT DATA TO THE ALU
 input [2:0] SELECT;       // THIS WILL DECIDE THE CORRESPONDING OUTPUT RESULT FROM THE OUTPUTS OF FUNCTIONAL UNITS
 output [7:0] RESULT;
 wire [7:0] FORWARD_OUT, ADD_OUT, AND_OUT, OR_OUT; // these will be the outputs of the functional units

 FORWARD forward_result(DATA2, FORWARD_OUT); //FORWARD FUNCTION  
 ADD add_result(DATA1,DATA2, ADD_OUT);      //ADD FUNCTION
 AND and_result(DATA1, DATA2, AND_OUT);     //AND  FUNCTION
 OR or_result(DATA1, DATA2, OR_OUT);        //OR FUNCTION
 MUX mux_result(SELECT,FORWARD_OUT, ADD_OUT, AND_OUT, OR_OUT,RESULT);  // RESULT OUTPUT WILL BE DECIDED FROM THE OUTPUTS OF THE FUNCTIONAL UNITS
 
endmodule





module FORWARD(DATA2, FORWARD_OUT);   //JUST FORWARD THE OUTPUT (loadi,mov)
 input [7:0] DATA2;
 output [7:0] FORWARD_OUT;

 assign  #1FORWARD_OUT=DATA2;  //DELAY 1 UNIT

endmodule


module ADD(DATA1,DATA2, ADD_OUT); //Addition and substraction operations
input [7:0] DATA1,DATA2;
output [7:0]ADD_OUT;

assign  #2ADD_OUT=DATA1+DATA2;  //DELAY 2 UNITS

endmodule

module AND(DATA1, DATA2, AND_OUT); //AND OPERATION
 input [7:0] DATA1,DATA2;
 output [7:0] AND_OUT;

 assign  #1AND_OUT=DATA1&DATA2;  //DELAY 1 UNIT

endmodule

module OR(DATA1, DATA2, OR_OUT); //OR OPERATION
 input [7:0] DATA1,DATA2;
 output [7:0] OR_OUT;

 assign  #1OR_OUT=DATA1|DATA2;  //DELAY 1 UNIT

endmodule


module MUX(SELECT,FORWARD_OUT, ADD_OUT, AND_OUT, OR_OUT,RESULT); //THE MUX IS USED TO GET THE RESULT OF THE DESIRED FUNCTION

input [7:0] FORWARD_OUT, ADD_OUT, AND_OUT, OR_OUT;
input [2:0] SELECT;
output reg [7:0] RESULT;



always @ (SELECT,FORWARD_OUT, ADD_OUT, AND_OUT, OR_OUT)
begin
  if(SELECT == 3'b000)
  begin
    RESULT = FORWARD_OUT;
  end

  else if(SELECT == 3'b001)
  begin
    RESULT = ADD_OUT;
  end  

  else if(SELECT == 3'b010)
  begin
    RESULT = AND_OUT;
  end

  else if(SELECT == 3'b011)
  begin
    RESULT = OR_OUT;
  end  

  else
  begin
    RESULT = OR_OUT;
  end  
end
endmodule

Lab5/second.v
//Wrong

module testbench;
 reg [2:0] READREG1,READREG2,WRITEREG;
 reg [7:0] WRITEDATA;
 wire [7:0] REGOUT1,REGOUT2;
 reg RESET,WRITEENABLE;
 reg CLOCK;


 reg_file model2(WRITEDATA,REGOUT1,REGOUT2,WRITEREG,READREG1,READREG2,WRITEENABLE,CLOCK,RESET);

 initial
 begin
  CLOCK = 0;
  forever 
   #5 CLOCK=~CLOCK;  
 end

 initial
 begin
  $dumpfile("wavedata2.vcd");
  $dumpvars(0,model2);
  #100 $finish;
 end

 initial
  begin
   READREG1=3'b000;
   READREG2=3'b001;
   WRITEENABLE=1'b0;
   RESET=1'b0;
   

   #5
   WRITEREG=3'b001;
   WRITEDATA=8'b00001111;
   WRITEENABLE=1'b1;

  end
endmodule









//8*8 register file
module reg_file(IN,OUT1,OUT2,INADDRESS,OUT1ADDRESS,OUT2ADDRESS,WRITE,CLK,RESET);
 input [7:0] IN;
 input [2:0] OUT1ADDRESS,OUT2ADDRESS,INADDRESS;
 input CLK,WRITE,RESET;
 output reg [7:0] OUT1,OUT2;

 reg [7:0] register [0:7];   //register1,register2,register3,register4,register5,register6,register7;



//this block will read the register value requested in OUT1ADDRESS and send it through OUT1


/*
 always @(OUT1ADDRESS)
 begin
  if(OUT1ADDRESS==3'b000)
  begin
   OUT1=register0;
  end

  else if(OUT1ADDRESS==3'b001)
  begin
   OUT1=register1;
  end

  else if(OUT1ADDRESS==3'b010)
  begin
   OUT1=register2;
  end

  else if(OUT1ADDRESS==3'b011)
  begin
   OUT1=register3;
  end

  else if(OUT1ADDRESS==3'b100)
  begin
   OUT1=register4;
  end

  else if(OUT1ADDRESS==3'b101)
  begin
   OUT1=register5;
  end

  else if(OUT1ADDRESS==3'b110)
  begin
   OUT1=register6;
  end 

  else 
  begin
   OUT1=register7;
  end
 end 

*/



//this block will read the register value requested in OUT2ADDRESS and send it through OUT2
 always @(OUT2ADDRESS)
 begin
  if(OUT2ADDRESS==3'b000)
  begin
   OUT2=register0;
  end

  else if(OUT2ADDRESS==3'b001)
  begin
   OUT2=register1;
  end

  else if(OUT2ADDRESS==3'b010)
  begin
   OUT2=register2;
  end

  else if(OUT2ADDRESS==3'b011)
  begin
   OUT2=register3;
  end

  else if(OUT2ADDRESS==3'b100)
  begin
   OUT2=register4;
  end

  else if(OUT2ADDRESS==3'b101)
  begin
   OUT2=register5;
  end

  else if(OUT2ADDRESS==3'b110)
  begin
   OUT2=register6;
  end 

  else 
  begin
   OUT2=register7;
  end
 end 

//At the positive edge of the clock if the write signal is high then the value IN should be wriiten to the register at the address INADDRESS

always @(posedge CLK)
begin
 if(WRITE==1'b1)
 begin
  if(INADDRESS==3'b000)
   begin
    register0=IN;
   end

  else if(INADDRESS==3'b001)
   begin
    register1=IN;
   end

  else if(INADDRESS==3'b010)
   begin
    register2=IN;
   end

  else if(INADDRESS==3'b011)
   begin
    register3=IN;
   end

  else if(INADDRESS==3'b100)
   begin
    register4=IN;
   end

  else if(INADDRESS==3'b101)
   begin
    register5=IN;
   end

  else if(INADDRESS==3'b110)
   begin
    register6=IN;
   end 

  else 
   begin
    register7=IN;
   end
 end



end


//At the rising edge of the CLK if RESET is high, all the registers should be written to zero

always @(posedge CLK)
begin
 if (RESET==1'b1)
 begin
   register0=8'b00000000;
   register1=8'b00000000;
   register2=8'b00000000;
   register3=8'b00000000;
   register4=8'b00000000;
   register5=8'b00000000;
   register6=8'b00000000;
   register7=8'b00000000;
 end
end





endmodule

lab5part3/submission/submit/cpu_tb.v
// Computer Architecture (CO224) - Lab 05
// Design: Testbench of Integrated CPU of Simple Processor
// Author: Isuru Nawinne
`include "cpu(group03_part3).v"

module cpu_tb;

    reg CLK, RESET;
    wire [31:0] PC;
    wire [31:0] INSTRUCTION;
    
    /* 
    ------------------------
     SIMPLE INSTRUCTION MEM
    ------------------------
    */
    
    // TODO: Initialize an array of registers (8x1024) named 'instr_mem' to be used as instruction memory
    reg [7:0] instr_mem [0:1023];
    
    // TODO: Create combinational logic to support CPU instruction fetching, given the Program Counter(PC) value 
    //       (make sure you include the delay for instruction fetching here)

   
    assign #2 INSTRUCTION ={instr_mem[PC+3], instr_mem[PC+2], instr_mem[PC+1], instr_mem[PC]};
    


    
    initial
    begin
        // Initialize instruction memory with the set of instructions you need execute on CPU
        
        // METHOD 1: manually loading instructions to instr_mem
        //{instr_mem[10'd3], instr_mem[10'd2], instr_mem[10'd1], instr_mem[10'd0]} = 32'b00000000000001000000000000000101;
        //{instr_mem[10'd7], instr_mem[10'd6], instr_mem[10'd5], instr_mem[10'd4]} = 32'b00000000000000100000000000001001;
        //{instr_mem[10'd11], instr_mem[10'd10], instr_mem[10'd9], instr_mem[10'd8]} = 32'b00000010000001100000010000000010;
        
        // METHOD 2: loading instr_mem content from instr_mem.mem file
        $readmemb("instr_mem.mem", instr_mem);
    end
    
    /* 
    -----
     CPU
    -----
    */
    cpu mycpu(PC, INSTRUCTION, CLK, RESET);

    initial
    begin
    
        // generate files needed to plot the waveform using GTKWave
        $dumpfile("cpu_wavedata.vcd");
		$dumpvars(0, cpu_tb);
        
        CLK = 1'b0;
        RESET = 1'b0;
        
        // TODO: Reset the CPU (by giving a pulse to RESET signal) to start the program execution
      //  RESET=1'b1;
      //  #5
      //  RESET=1'b0;
      //  #120
     //   RESET=1'b1;

        
        // finish simulation after some time
        #500
        $finish;
        
    end
    
    // clock signal generation
    always
        #4 CLK = ~CLK;
        

endmodule

lab5part3/submission/cpu_wavedata.vcd
$date
	Wed Jan 26 09:09:48 2022
$end
$version
	Icarus Verilog
$end
$timescale
	1s
$end
$scope module cpu_tb $end
$var wire 32 ! PC [31:0] $end
$var wire 32 " INSTRUCTION [31:0] $end
$var reg 1 # CLK $end
$var reg 1 $ RESET $end
$scope module mycpu $end
$var wire 1 # CLK $end
$var wire 32 % INSTRUCTION [31:0] $end
$var wire 1 $ RESET $end
$var wire 3 & WRITEREG [2:0] $end
$var wire 1 ' WRITEENABLE $end
$var wire 8 ( VALUE2 [7:0] $end
$var wire 8 ) REGOUT2COMPLIMENT [7:0] $end
$var wire 8 * REGOUT2 [7:0] $end
$var wire 8 + REGOUT1 [7:0] $end
$var wire 3 , READREG2 [2:0] $end
$var wire 3 - READREG1 [2:0] $end
$var wire 32 . PCOUT [31:0] $end
$var wire 8 / OPERAND2 [7:0] $end
$var wire 8 0 OPCODE [7:0] $end
$var wire 1 1 MUXREGOUT2 $end
$var wire 1 2 MUXIMMEDIATE $end
$var wire 8 3 IMMEDIATE [7:0] $end
$var wire 8 4 ALURESULT [7:0] $end
$var wire 3 5 ALUOP [2:0] $end
$var reg 32 6 PC [31:0] $end
$scope module ValueOPERAND2 $end
$var wire 8 7 IMMEDIATE [7:0] $end
$var wire 8 8 VALUE2 [7:0] $end
$var wire 1 2 MUXIMMEDIATE $end
$var reg 8 9 OPERAND2 [7:0] $end
$upscope $end
$scope module alu_result $end
$var wire 8 : DATA2 [7:0] $end
$var wire 3 ; SELECT [2:0] $end
$var wire 8 < RESULT [7:0] $end
$var wire 8 = OR_OUT [7:0] $end
$var wire 8 > FORWARD_OUT [7:0] $end
$var wire 8 ? DATA1 [7:0] $end
$var wire 8 @ AND_OUT [7:0] $end
$var wire 8 A ADD_OUT [7:0] $end
$scope module add_result $end
$var wire 8 B DATA2 [7:0] $end
$var wire 8 C DATA1 [7:0] $end
$var wire 8 D ADD_OUT [7:0] $end
$upscope $end
$scope module and_result $end
$var wire 8 E AND_OUT [7:0] $end
$var wire 8 F DATA2 [7:0] $end
$var wire 8 G DATA1 [7:0] $end
$upscope $end
$scope module forward_result $end
$var wire 8 H DATA2 [7:0] $end
$var wire 8 I FORWARD_OUT [7:0] $end
$upscope $end
$scope module mux_result $end
$var wire 8 J ADD_OUT [7:0] $end
$var wire 8 K AND_OUT [7:0] $end
$var wire 8 L FORWARD_OUT [7:0] $end
$var wire 3 M SELECT [2:0] $end
$var wire 8 N OR_OUT [7:0] $end
$var reg 8 O RESULT [7:0] $end
$upscope $end
$scope module or_result $end
$var wire 8 P DATA2 [7:0] $end
$var wire 8 Q OR_OUT [7:0] $end
$var wire 8 R DATA1 [7:0] $end
$upscope $end
$upscope $end
$scope module compliment_operation $end
$var wire 8 S REGOUT2 [7:0] $end
$var reg 8 T REGOUT2COMPLIMENT [7:0] $end
$upscope $end
$scope module control_signals $end
$var wire 8 U OPCODE [7:0] $end
$var reg 3 V ALUOP [2:0] $end
$var reg 1 2 MUXIMMEDIATE $end
$var reg 1 1 MUXREGOUT2 $end
$var reg 1 ' WRITEENABLE $end
$upscope $end
$scope module pc_adder $end
$var wire 32 W PC [31:0] $end
$var wire 32 X PCOUT [31:0] $end
$upscope $end
$scope module register_operation $end
$var wire 1 # CLK $end
$var wire 8 Y IN [7:0] $end
$var wire 3 Z INADDRESS [2:0] $end
$var wire 3 [ OUT1ADDRESS [2:0] $end
$var wire 3 \ OUT2ADDRESS [2:0] $end
$var wire 1 $ RESET $end
$var wire 1 ' WRITE $end
$var reg 8 ] OUT1 [7:0] $end
$var reg 8 ^ OUT2 [7:0] $end
$upscope $end
$scope module sub_or_not $end
$var wire 1 1 MUXREGOUT2 $end
$var wire 8 _ REGOUT2 [7:0] $end
$var wire 8 ` REGOUT2COMPLIMENT [7:0] $end
$var reg 8 a VALUE2 [7:0] $end
$upscope $end
$upscope $end
$upscope $end
$enddefinitions $end
#0
$dumpvars
bx a
bx `
bx _
bx ^
bx ]
bx \
bx [
bx Z
bx Y
bx X
b11111111111111111111111111111100 W
bx V
bx U
bx T
bx S
bx R
bx Q
bx P
bx O
bx N
bx M
bx L
bx K
bx J
bx I
bx H
bx G
bx F
bx E
bx D
bx C
bx B
bx A
bx @
bx ?
bx >
bx =
bx <
bx ;
bx :
bx 9
bx 8
bx 7
b11111111111111111111111111111100 6
bx 5
bx 4
bx 3
x2
x1
bx 0
bx /
bx .
bx -
bx ,
bx +
bx *
bx )
bx (
x'
bx &
bx %
0$
0#
bx "
b11111111111111111111111111111100 !
$end
#1
b0 .
b0 X
#4
1#
#5
b0 !
b0 6
b0 W
#6
b100 .
b100 X
#7
b101 /
b101 9
b101 :
b101 B
b101 F
b101 H
b101 P
b0 0
b0 U
b0 -
b0 [
b101 ,
b101 \
b101 3
b101 7
b100 &
b100 Z
b1000000000000000101 "
b1000000000000000101 %
#8
b101 4
b101 <
b101 O
b101 Y
b0x0x @
b0x0x E
b0x0x K
bx1x1 =
bx1x1 N
bx1x1 Q
1'
11
12
b0 5
b0 ;
b0 M
b0 V
b101 >
b101 I
b101 L
0#
#12
1#
#13
b100 !
b100 6
b100 W
#14
b1000 .
b1000 X
#15
b1001 /
b1001 9
b1001 :
b1001 B
b1001 F
b1001 H
b1001 P
b1 ,
b1 \
b1001 3
b1001 7
b10 &
b10 Z
b100000000000001001 "
b100000000000001001 %
#16
b1001 4
b1001 <
b1001 O
b1001 Y
b0x00x @
b0x00x E
b0x00x K
bx1xx1 =
bx1xx1 N
bx1xx1 Q
b1001 >
b1001 I
b1001 L
0#
#20
1#
#21
b1000 !
b1000 6
b1000 W
#22
b1100 .
b1100 X
#23
b10 /
b10 9
b10 :
b10 B
b10 F
b10 H
b10 P
b10 0
b10 U
b100 -
b100 [
b10 ,
b10 \
b10 3
b10 7
b110 &
b110 Z
b10000001100000010000000010 "
b10000001100000010000000010 %
#24
bx /
bx 9
bx :
bx B
bx F
bx H
bx P
bx 4
bx <
bx O
bx Y
b0x0 @
b0x0 E
b0x0 K
bx1x =
bx1x N
bx1x Q
02
b1 5
b1 ;
b1 M
b1 V
b10 >
b10 I
b10 L
0#
#25
b1001 /
b1001 9
b1001 :
b1001 B
b1001 F
b1001 H
b1001 P
b1001 (
b1001 8
b1001 a
bx @
bx E
bx K
bx =
bx N
bx Q
bx >
bx I
bx L
b1001 *
b1001 S
b1001 ^
b1001 _
b101 +
b101 ?
b101 C
b101 G
b101 R
b101 ]
#26
b1001 >
b1001 I
b1001 L
b11110111 )
b11110111 T
b11110111 `
b1101 =
b1101 N
b1101 Q
b1 @
b1 E
b1 K
#27
b1110 4
b1110 <
b1110 O
b1110 Y
b1110 A
b1110 D
b1110 J
#28
1#
#29
b1100 !
b1100 6
b1100 W
#30
b10000 .
b10000 X
#31
b1 0
b1 U
b0 -
b0 [
b110 ,
b110 \
b110 3
b110 7
b0 &
b0 Z
b1000000000000000000000110 "
b1000000000000000000000110 %
#32
b1001 4
b1001 <
b1001 O
b1001 Y
b0 5
b0 ;
b0 M
b0 V
0#
#33
b1110 /
b1110 9
b1110 :
b1110 B
b1110 F
b1110 H
b1110 P
b1110 (
b1110 8
b1110 a
b1110 *
b1110 S
b1110 ^
b1110 _
bx +
bx ?
bx C
bx G
bx R
bx ]
#34
b1110 4
b1110 <
b1110 O
b1110 Y
b1110 >
b1110 I
b1110 L
b11110010 )
b11110010 T
b11110010 `
bx111x =
bx111x N
bx111x Q
b0xxx0 @
b0xxx0 E
b0xxx0 K
#35
bx A
bx D
bx J
#36
1#
#37
b10000 !
b10000 6
b10000 W
#38
b10100 .
b10100 X
#39
b0 0
b0 U
b1 ,
b1 \
b1 3
b1 7
b1 &
b1 Z
b1110 +
b1110 ?
b1110 C
b1110 G
b1110 R
b1110 ]
b10000000000000001 "
b10000000000000001 %
#40
b1 /
b1 9
b1 :
b1 B
b1 F
b1 H
b1 P
12
b1110 =
b1110 N
b1110 Q
b1110 @
b1110 E
b1110 K
0#
#41
b1 4
b1 <
b1 O
b1 Y
bx (
bx 8
bx a
b0 @
b0 E
b0 K
b1111 =
b1111 N
b1111 Q
b1 >
b1 I
b1 L
bx *
bx S
bx ^
bx _
#42
bx )
bx T
bx `
b1111 A
b1111 D
b1111 J
#44
1#
#45
b10100 !
b10100 6
b10100 W
#46
b11000 .
b11000 X
#47
b1 (
b1 8
b1 a
b10 0
b10 U
b10 -
b10 [
b10 &
b10 Z
b1 *
b1 S
b1 ^
b1 _
b10000000100000001000000001 "
b10000000100000001000000001 %
#48
b1111 4
b1111 <
b1111 O
b1111 Y
02
b1 5
b1 ;
b1 M
b1 V
b11111111 )
b11111111 T
b11111111 `
0#
#49
b1001 +
b1001 ?
b1001 C
b1001 G
b1001 R
b1001 ]
#50
b1001 =
b1001 N
b1001 Q
b1 @
b1 E
b1 K
#51
b1010 4
b1010 <
b1010 O
b1010 Y
b1010 A
b1010 D
b1010 J
#52
1#
#53
b11000 !
b11000 6
b11000 W
#54
b11100 .
b11100 X
#55
bx 0
bx U
bx -
bx [
bx ,
bx \
bx 3
bx 7
bx &
bx Z
b1010 +
b1010 ?
b1010 C
b1010 G
b1010 R
b1010 ]
bx "
bx %
#56
b1011 4
b1011 <
b1011 O
b1011 Y
0'
b11 5
b11 ;
b11 M
b11 V
b1011 =
b1011 N
b1011 Q
b0 @
b0 E
b0 K
0#
#57
bx /
bx 9
bx :
bx B
bx F
bx H
bx P
bx (
bx 8
bx a
bx *
bx S
bx ^
bx _
bx +
bx ?
bx C
bx G
bx R
bx ]
b1011 A
b1011 D
b1011 J
#58
bx 4
bx <
bx O
bx Y
bx >
bx I
bx L
bx )
bx T
bx `
bx =
bx N
bx Q
bx @
bx E
bx K
#59
bx A
bx D
bx J
#60
1#
#61
b11100 !
b11100 6
b11100 W
#62
b100000 .
b100000 X
#64
0#
#68
1#
#69
b100000 !
b100000 6
b100000 W
#70
b100100 .
b100100 X
#72
0#
#76
1#
#77
b100100 !
b100100 6
b100100 W
#78
b101000 .
b101000 X
#80
0#
#84
1#
#85
b101000 !
b101000 6
b101000 W
#86
b101100 .
b101100 X
#88
0#
#92
1#
#93
b101100 !
b101100 6
b101100 W
#94
b110000 .
b110000 X
#96
0#
#100
1#
#101
b110000 !
b110000 6
b110000 W
#102
b110100 .
b110100 X
#104
0#
#108
1#
#109
b110100 !
b110100 6
b110100 W
#110
b111000 .
b111000 X
#112
0#
#116
1#
#117
b111000 !
b111000 6
b111000 W
#118
b111100 .
b111100 X
#120
0#
#124
1#
#125
b111100 !
b111100 6
b111100 W
#126
b1000000 .
b1000000 X
#128
0#
#132
1#
#133
b1000000 !
b1000000 6
b1000000 W
#134
b1000100 .
b1000100 X
#136
0#
#140
1#
#141
b1000100 !
b1000100 6
b1000100 W
#142
b1001000 .
b1001000 X
#144
0#
#148
1#
#149
b1001000 !
b1001000 6
b1001000 W
#150
b1001100 .
b1001100 X
#152
0#
#156
1#
#157
b1001100 !
b1001100 6
b1001100 W
#158
b1010000 .
b1010000 X
#160
0#
#164
1#
#165
b1010000 !
b1010000 6
b1010000 W
#166
b1010100 .
b1010100 X
#168
0#
#172
1#
#173
b1010100 !
b1010100 6
b1010100 W
#174
b1011000 .
b1011000 X
#176
0#
#180
1#
#181
b1011000 !
b1011000 6
b1011000 W
#182
b1011100 .
b1011100 X
#184
0#
#188
1#
#189
b1011100 !
b1011100 6
b1011100 W
#190
b1100000 .
b1100000 X
#192
0#
#196
1#
#197
b1100000 !
b1100000 6
b1100000 W
#198
b1100100 .
b1100100 X
#200
0#
#204
1#
#205
b1100100 !
b1100100 6
b1100100 W
#206
b1101000 .
b1101000 X
#208
0#
#212
1#
#213
b1101000 !
b1101000 6
b1101000 W
#214
b1101100 .
b1101100 X
#216
0#
#220
1#
#221
b1101100 !
b1101100 6
b1101100 W
#222
b1110000 .
b1110000 X
#224
0#
#228
1#
#229
b1110000 !
b1110000 6
b1110000 W
#230
b1110100 .
b1110100 X
#232
0#
#236
1#
#237
b1110100 !
b1110100 6
b1110100 W
#238
b1111000 .
b1111000 X
#240
0#
#244
1#
#245
b1111000 !
b1111000 6
b1111000 W
#246
b1111100 .
b1111100 X
#248
0#
#252
1#
#253
b1111100 !
b1111100 6
b1111100 W
#254
b10000000 .
b10000000 X
#256
0#
#260
1#
#261
b10000000 !
b10000000 6
b10000000 W
#262
b10000100 .
b10000100 X
#264
0#
#268
1#
#269
b10000100 !
b10000100 6
b10000100 W
#270
b10001000 .
b10001000 X
#272
0#
#276
1#
#277
b10001000 !
b10001000 6
b10001000 W
#278
b10001100 .
b10001100 X
#280
0#
#284
1#
#285
b10001100 !
b10001100 6
b10001100 W
#286
b10010000 .
b10010000 X
#288
0#
#292
1#
#293
b10010000 !
b10010000 6
b10010000 W
#294
b10010100 .
b10010100 X
#296
0#
#300
1#
#301
b10010100 !
b10010100 6
b10010100 W
#302
b10011000 .
b10011000 X
#304
0#
#308
1#
#309
b10011000 !
b10011000 6
b10011000 W
#310
b10011100 .
b10011100 X
#312
0#
#316
1#
#317
b10011100 !
b10011100 6
b10011100 W
#318
b10100000 .
b10100000 X
#320
0#
#324
1#
#325
b10100000 !
b10100000 6
b10100000 W
#326
b10100100 .
b10100100 X
#328
0#
#332
1#
#333
b10100100 !
b10100100 6
b10100100 W
#334
b10101000 .
b10101000 X
#336
0#
#340
1#
#341
b10101000 !
b10101000 6
b10101000 W
#342
b10101100 .
b10101100 X
#344
0#
#348
1#
#349
b10101100 !
b10101100 6
b10101100 W
#350
b10110000 .
b10110000 X
#352
0#
#356
1#
#357
b10110000 !
b10110000 6
b10110000 W
#358
b10110100 .
b10110100 X
#360
0#
#364
1#
#365
b10110100 !
b10110100 6
b10110100 W
#366
b10111000 .
b10111000 X
#368
0#
#372
1#
#373
b10111000 !
b10111000 6
b10111000 W
#374
b10111100 .
b10111100 X
#376
0#
#380
1#
#381
b10111100 !
b10111100 6
b10111100 W
#382
b11000000 .
b11000000 X
#384
0#
#388
1#
#389
b11000000 !
b11000000 6
b11000000 W
#390
b11000100 .
b11000100 X
#392
0#
#396
1#
#397
b11000100 !
b11000100 6
b11000100 W
#398
b11001000 .
b11001000 X
#400
0#
#404
1#
#405
b11001000 !
b11001000 6
b11001000 W
#406
b11001100 .
b11001100 X
#408
0#
#412
1#
